linked_list/Linked_List.py
linked_list/__init__.py
py_linked_list-1.0.0.dist-info/LICENSE.txt
py_linked_list-1.0.0.dist-info/METADATA
py_linked_list-1.0.0.dist-info/WHEEL
py_linked_list-1.0.0.dist-info/top_level.txt
py_linked_list-1.0.0.dist-info/RECORD
