Metadata-Version: 2.1
Name: py_linked_list
Version: 1.0.0
Summary: A Python package with simple implementation of a singly linked list with various utility functions.
Author-email: Aman Kumar <amankumar84349@gmail.com>
Project-URL: Homepage, https://github.com/aman2457/Linked_List
Project-URL: Issues, https://github.com/aman2457/Linked_List
Keywords: linked list,singly linked list,data structure,python,utility functions,linked list operations
Classifier: License :: OSI Approved :: MIT License
Classifier: Programming Language :: Python :: 3
Classifier: Programming Language :: Python :: 3.7
Classifier: Operating System :: OS Independent
Classifier: Intended Audience :: Developers
Classifier: Intended Audience :: Education
Classifier: Intended Audience :: End Users/Desktop
Classifier: Intended Audience :: Science/Research
License-File: LICENSE.txt
